civ4save/__init__.py
civ4save/__main__.py
civ4save/cli.py
civ4save/save_file.py
civ4save/utils.py
civ4save/xml_files.py
civ4save/contrib/__init__.py
civ4save/contrib/civs.py
civ4save/contrib/leaders.py
civ4save/contrib/data/civs.json
civ4save/contrib/data/leaders.json
civ4save/contrib/data/text_map.json
civ4save/objects/__init__.py
civ4save/objects/game_state.py
civ4save/objects/player.py
civ4save/objects/plot.py
civ4save/objects/settings.py
civ4save/vanilla/__init__.py
civ4save/vanilla/enums.py
civ4save/vanilla/structure.py
civ4save-0.7.0.dist-info/METADATA
civ4save-0.7.0.dist-info/WHEEL
civ4save-0.7.0.dist-info/entry_points.txt
civ4save-0.7.0.dist-info/top_level.txt
civ4save-0.7.0.dist-info/RECORD
