Metadata-Version: 2.1
Name: civ4save
Version: 0.7.0
Summary: Extract data from a .CivBeyondSwordSave file
Author-email: Dan Davis <dan@dandavis.dev>
License: GNU GENERAL PUBLIC LICENSE
Project-URL: Homepage, https://github.com/danofsteel32/civ4save
Keywords: civ,civilization,savefile
Classifier: License :: OSI Approved :: GNU Affero General Public License v3
Classifier: Topic :: Games/Entertainment :: Turn Based Strategy
Requires-Python: >=3.7
Requires-Dist: attrs
Requires-Dist: click
Requires-Dist: construct
Requires-Dist: importlib-resources (>=5.9.0)
Requires-Dist: Jinja2
Requires-Dist: lazy-property
Requires-Dist: rich
Requires-Dist: xmltodict
Provides-Extra: dev
Requires-Dist: black ; extra == 'dev'
Requires-Dist: flake8 ; extra == 'dev'
Requires-Dist: flake8-isort ; extra == 'dev'
Requires-Dist: flake8-docstrings ; extra == 'dev'
Requires-Dist: mypy ; extra == 'dev'
Requires-Dist: pytest ; extra == 'dev'
Requires-Dist: tox ; extra == 'dev'
